zq_logger/__init__.py
zq_logger-0.1.dist-info/METADATA
zq_logger-0.1.dist-info/WHEEL
zq_logger-0.1.dist-info/top_level.txt
zq_logger-0.1.dist-info/RECORD
